spatial_reasoning/__init__.py
spatial_reasoning/api.py
spatial_reasoning/run_cli.py
spatial_reasoning/agents/__init__.py
spatial_reasoning/agents/agent_factory.py
spatial_reasoning/agents/base_agent.py
spatial_reasoning/agents/gemini_agent.py
spatial_reasoning/agents/openai_agent.py
spatial_reasoning/data/__init__.py
spatial_reasoning/data/base_data.py
spatial_reasoning/data/cell_data.py
spatial_reasoning/data/detection_data.py
spatial_reasoning/prompts/__init__.py
spatial_reasoning/prompts/base_prompt.py
spatial_reasoning/prompts/detection_prompts.py
spatial_reasoning/tasks/__init__.py
spatial_reasoning/tasks/advanced_multi_reasoning_model_task.py
spatial_reasoning/tasks/advanced_reasoning_model_task.py
spatial_reasoning/tasks/base_task.py
spatial_reasoning/tasks/gemini_task.py
spatial_reasoning/tasks/stream_advanced_reasoning_model_task.py
spatial_reasoning/tasks/vanilla_reasoning_model_task.py
spatial_reasoning/tasks/vision_model_task.py
spatial_reasoning/utils/__init__.py
spatial_reasoning/utils/image_utils.py
spatial_reasoning/utils/io_utils.py
spatial_reasoning-0.2.1.dist-info/licenses/LICENSE
spatial_reasoning-0.2.1.dist-info/METADATA
spatial_reasoning-0.2.1.dist-info/WHEEL
spatial_reasoning-0.2.1.dist-info/entry_points.txt
spatial_reasoning-0.2.1.dist-info/top_level.txt
spatial_reasoning-0.2.1.dist-info/RECORD
