Metadata-Version: 2.4
Name: spatial-reasoning
Version: 0.2.1
Summary: A PyPI package for object detection using advanced vision models
Home-page: https://github.com/QasimWani/spatial-reasoning
Author: Qasim Wani
Author-email: Qasim Wani <qasim31wani@gmail.com>
License: MIT
Project-URL: Homepage, https://github.com/QasimWani/spatial-reasoning
Project-URL: Bug Tracker, https://github.com/QasimWani/spatial-reasoning/issues
Project-URL: Documentation, https://github.com/QasimWani/spatial-reasoning#readme
Project-URL: Source Code, https://github.com/QasimWani/spatial-reasoning
Keywords: computer vision,object detection,AI,machine learning,OpenAI,Gemini
Classifier: Development Status :: 3 - Alpha
Classifier: Intended Audience :: Developers
Classifier: Intended Audience :: Science/Research
Classifier: License :: OSI Approved :: MIT License
Classifier: Operating System :: OS Independent
Classifier: Programming Language :: Python :: 3
Classifier: Programming Language :: Python :: 3.8
Classifier: Programming Language :: Python :: 3.9
Classifier: Programming Language :: Python :: 3.10
Classifier: Programming Language :: Python :: 3.11
Classifier: Topic :: Scientific/Engineering :: Artificial Intelligence
Classifier: Topic :: Scientific/Engineering :: Image Recognition
Requires-Python: >=3.8
License-File: LICENSE
Requires-Dist: numpy>=1.21.0
Requires-Dist: torch>=2.0.0
Requires-Dist: torchvision>=0.15.0
Requires-Dist: Pillow>=9.0.0
Requires-Dist: opencv-python>=4.5.0
Requires-Dist: matplotlib>=3.3.0
Requires-Dist: scipy>=1.7.0
Requires-Dist: requests>=2.25.0
Requires-Dist: python-dotenv>=0.19.0
Requires-Dist: openai>=1.0.0
Requires-Dist: google-genai
Requires-Dist: transformers>=4.30.0
Requires-Dist: datasets>=2.0.0
Requires-Dist: accelerate>=1.6.0
Provides-Extra: dev
Requires-Dist: pytest>=7.0.0; extra == "dev"
Requires-Dist: black>=22.0.0; extra == "dev"
Requires-Dist: flake8>=4.0.0; extra == "dev"
Requires-Dist: mypy>=0.990; extra == "dev"
Dynamic: author
Dynamic: home-page
Dynamic: license-file
Dynamic: requires-python
